setup.py
geoip/__init__.py
geoip/admin.py
geoip/conf.py
geoip/decorators.py
geoip/exceptions.py
geoip/middleware.py
geoip/models.py
geoip/settings.py
geoip/views.py
geoipredirect.egg-info/PKG-INFO
geoipredirect.egg-info/SOURCES.txt
geoipredirect.egg-info/dependency_links.txt
geoipredirect.egg-info/top_level.txt