Metadata-Version: 1.0
Name: geoipredirect
Version: 0.2.0
Summary: Django middleware to insert a redirect lightbox based on users IP
Home-page: https://github.com/jaymzcd/geoip-redirect
Author: Jaymz Campbell
Author-email: jaymz@jaymz.eu
License: UNKNOWN
Platform: UNKNOWN
